repokid/__init__.py
repokid/exceptions.py
repokid/plugin.py
repokid/py.typed
repokid/role.py
repokid/types.py
repokid/cli/__init__.py
repokid/cli/dispatcher_cli.py
repokid/cli/repokid_cli.py
repokid/commands/__init__.py
repokid/commands/repo.py
repokid/commands/role.py
repokid/commands/role_cache.py
repokid/commands/schedule.py
repokid/datasource/__init__.py
repokid/datasource/access_advisor.py
repokid/datasource/iam.py
repokid/datasource/plugin.py
repokid/dispatcher/__init__.py
repokid/dispatcher/types.py
repokid/filters/__init__.py
repokid/filters/utils.py
repokid/filters/age/__init__.py
repokid/filters/blocklist/__init__.py
repokid/filters/exclusive/__init__.py
repokid/filters/lambda/__init__.py
repokid/filters/optout/__init__.py
repokid/hooks/__init__.py
repokid/hooks/loggers/__init__.py
repokid/lib/__init__.py
repokid/utils/__init__.py
repokid/utils/dynamo.py
repokid/utils/iam.py
repokid/utils/logging.py
repokid/utils/permissions.py
repokid/utils/roledata.py
tests/__init__.py
tests/conftest.py
tests/test_commands.py
tests/test_dispatcher_cli.py
tests/test_hooks.py
tests/test_role.py
tests/test_roledata.py
tests/vars.py
tests/artifacts/__init__.py
tests/artifacts/hook/__init__.py
tests/datasource/__init__.py
tests/datasource/conftest.py
tests/datasource/test_access_advisor.py
tests/datasource/test_iam.py
tests/filters/__init__.py
tests/filters/test_age.py
repokid-0.19.8.dist-info/AUTHORS
repokid-0.19.8.dist-info/LICENSE
repokid-0.19.8.dist-info/METADATA
repokid-0.19.8.dist-info/WHEEL
repokid-0.19.8.dist-info/entry_points.txt
repokid-0.19.8.dist-info/top_level.txt
repokid-0.19.8.dist-info/RECORD
