Metadata-Version: 2.1
Name: repokid
Version: 0.19.8
Summary: AWS Least Privilege for Distributed, High-Velocity Deployment
Home-page: https://github.com/Netflix/repokid
License: Apache 2.0
Keywords: aws,iam,access_advisor
Platform: UNKNOWN
Classifier: Development Status :: 5 - Production/Stable
Classifier: Intended Audience :: Developers
Classifier: Intended Audience :: System Administrators
Classifier: License :: OSI Approved :: Apache Software License
Classifier: Natural Language :: English
Classifier: Operating System :: OS Independent
Classifier: Programming Language :: Python :: 3.7
Classifier: Topic :: Security
Classifier: Topic :: System
Classifier: Topic :: System :: Systems Administration
Requires-Python: >=3.7
Requires-Dist: boto3 (<=1.17.71)
Requires-Dist: boto3-stubs[dynamodb,iam,sns,sqs] (<=1.17.71)
Requires-Dist: cloudaux
Requires-Dist: click
Requires-Dist: import-string
Requires-Dist: json-log-formatter
Requires-Dist: policyuniverse
Requires-Dist: requests
Requires-Dist: tabulate
Requires-Dist: tabview
Requires-Dist: tqdm
Requires-Dist: pip-tools
Requires-Dist: pydantic
Requires-Dist: python-dateutil
Requires-Dist: pytz
Requires-Dist: raven
Requires-Dist: twine
Requires-Dist: types-click
